{"dttime":"Nov 02,2010 11:29 PM","totals":
{"races":
{"U.S. House":
{"1":
{"votes":[
{"votes":81199,"id":"734"},
{"votes":32594,"id":"60582"},
{"votes":1383,"id":"744"},
{"votes":1292,"id":"61079"},
{"votes":957,"id":"60583"}],
"final":"734"},
"3":
{"votes":[
{"votes":63722,"id":"51753"},
{"votes":56549,"id":"9344"},
{"votes":2719,"id":"60586"},
{"votes":2457,"id":"60999"}]},
"2":
{"votes":[
{"votes":97438,"id":"9302"},
{"votes":67429,"id":"60691"},
{"votes":4653,"id":"60584"},
{"votes":2977,"id":"60585"}],
"final":"9302"},
"5":
{"votes":[
{"votes":6305,"id":"9174"},
{"votes":2924,"id":"60594"},
{"votes":321,"id":"59791"},
{"votes":251,"id":"60595"}]},
"4":
{"votes":[
{"votes":86395,"id":"60588"},
{"votes":72244,"id":"59348"},
{"votes":7525,"id":"60589"},
{"votes":2412,"id":"60593"}]},
"7":
{"votes":[
{"votes":66425,"id":"9291"},
{"votes":55578,"id":"60599"},
{"votes":5841,"id":"60600"}]},
"6":
{"votes":[
{"votes":97325,"id":"8993"},
{"votes":41958,"id":"60596"},
{"votes":3487,"id":"60598"}],
"final":"8993"}},
"Amendment":
{"62 - Definition of Person":
{"votes":[
{"votes":592278,"id":"3"},
{"votes":223561,"id":"2"}]},
"63 - Health Care":
{"votes":[
{"votes":444742,"id":"3"},
{"votes":361746,"id":"2"}]}},
"U.S. Senate":
{"":
{"votes":[
{"votes":434746,"id":"59911"},
{"votes":386845,"id":"61077"},
{"votes":18074,"id":"59783"},
{"votes":9774,"id":"61078"},
{"votes":8874,"id":"60998"},
{"votes":5587,"id":"60578"},
{"votes":2628,"id":"60579"}]}},
"Governor":
{"":
{"votes":[
{"votes":466533,"id":"60601"},
{"votes":317099,"id":"751"},
{"votes":81660,"id":"61076"},
{"votes":5390,"id":"60604"},
{"votes":3638,"id":"60607"},
{"votes":1491,"id":"53523"}],
"final":"60601"}}},
"precincts":
{"total":462,"reporting":182},
"abbr":"CO","name":"Colorado"},
"state":"CO","candidates":
{"744":"Grn|Swing|Gary Swing","59783":"Grn|Kinsey|Bob Kinsey","53523":"Una|Fiorino|Paul Fiorino","59348":"Dem|Markey|Betsy Markey","9344":"Dem|Salazar|John Salazar","60600":"Lib|Bailey|Buck Bailey","9302":"Dem|Polis|Jared Polis","60586":"Lib|Gilman|Gregory Gilman","60604":"Lib|Brown|Jaimes Brown","60584":"AmC|Goss|Jenna Goss","60585":"Lib|Harris|Curtis Harris","60582":"GOP|Fallon|Mike Fallon","60583":"AmC|Styskal|Chris Styskal","60588":"GOP|Gardner|Cory Gardner","60589":"AmC|Aden|Doug Aden","51753":"GOP|Tipton|Scott Tipton","3":"|No| No","2":"|Yes| Yes","734":"Dem|DeGette|Diana DeGette","61077":"GOP|Buck|Ken Buck","61076":"GOP|Maes|Dan Maes","61079":"Lib|Jones|Clint Jones","61078":"Lib|Stringer|Maclyn Stringer","60999":"Una|Segrest|Jake Segrest","60998":"INR|Napolitano|Jason Napolitano","751":"AmC|Tancredo|Tom Tancredo","59911":"Dem|Bennet|Michael Bennet","60579":"Una|Moromisato|J. Moromisato","60578":"Una|Miller|Charley Miller","60607":"Una|Clark|Jason Clark","60596":"Dem|Flerlage|John Flerlage","59791":"AmC|Scott|Brian Scott","60601":"Dem|Hickenlooper|John Hickenlooper","9174":"GOP|Lamborn|Doug Lamborn","60691":"GOP|Bailey|Stephen Bailey","60595":"Lib|Klaver|Jerell Klaver","60594":"Dem|Bradley|Kevin Bradley","9291":"Dem|Perlmutter|Ed Perlmutter","60593":"Una|Waszkiewicz|Ken Waszkiewicz","8993":"GOP|Coffman|Mike Coffman","60599":"GOP|Frazier|Ryan Frazier","60598":"Lib|McNealy|Rob McNealy"},
"total":0,"locals":
{}}