{"dttime":"Nov 02, 2010 08:24 PM","totals":
{"name":"Oklahoma","fix":
{"LeFlore":"Le Flore"},
"precincts":
{"total":349,"reporting":0},
"races":
{"U.S. House":
{"1":
{"votes":[
{"votes":0,"id":"1394"},
{"votes":0,"id":"60943"}]},
"3":
{"votes":[
{"votes":2817,"id":"1396"},
{"votes":586,"id":"59450"}]},
"2":
{"votes":[
{"votes":1074,"id":"50187"},
{"votes":600,"id":"61120"}]},
"5":
{"votes":[
{"votes":360,"id":"61119"},
{"votes":211,"id":"60945"},
{"votes":13,"id":"37460"},
{"votes":11,"id":"61056"}]},
"4":
{"votes":[
{"votes":0,"id":"1398"}],
"final":"1398"}},
"U.S. Senate":
{"":
{"votes":[
{"votes":4786,"id":"37351"},
{"votes":1747,"id":"38273"},
{"votes":125,"id":"59449"},
{"votes":48,"id":"61099"}]}},
"Question":
{"751 - English Official Language":
{"votes":[
{"votes":3473,"id":"2"},
{"votes":1065,"id":"3"}]},
"756 - Health Care":
{"votes":[
{"votes":1356,"id":"2"},
{"votes":865,"id":"3"}]},
"755 - Ban Intl or Islamic Law":
{"votes":[
{"votes":1499,"id":"2"},
{"votes":748,"id":"3"}]},
"746 - Voter ID":
{"votes":[
{"votes":4144,"id":"2"},
{"votes":1598,"id":"3"}]}},
"Governor":
{"":
{"votes":[
{"votes":7366,"id":"37501"},
{"votes":5343,"id":"57325"}]}}},
"abbr":"OK"},
"state":"OK","candidates":
{"59450":"Dem|Robbins|Frankie Robbins","37501":"GOP|Fallin|Mary Fallin","60945":"Dem|Coyle|Billy Coyle","61119":"GOP|Lankford|James Lankford","57325":"Dem|Askins|Jari Askins","61120":"GOP|Thompson|Charles Thompson","1398":"GOP|Cole|Tom Cole","37351":"GOP|Coburn|Tom Coburn","37460":"Ind|Duffe|Clark Duffe","3":"|No| No","2":"|Yes| Yes","59449":"Ind|Wallace|Stephen Wallace","50187":"Dem|Boren|Dan Boren","61056":"Ind|White|Dave White","1396":"GOP|Lucas|Frank Lucas","38273":"Dem|Rogers|Jim Rogers","1394":"GOP|Sullivan|John Sullivan","61099":"Ind|Dwyer|Ronald Dwyer","60943":"Ind|O'Dell|Angelia O'Dell"},
"total":0,"locals":
{}}